{"issue_id": "f-42", "version": 2, "updated_at": "2026-06-08T00:00:00Z", "items": [
  {"id": "AC-01", "desc": "定义 UploadTask 类型（id/fileName/progress/status/error/kbId）", "status": "passed"},
  {"id": "AC-02", "desc": "实现 addTask 添加任务到队列，返回唯一 taskId", "status": "passed"},
  {"id": "AC-03", "desc": "实现 updateProgress / markComplete / markFailed 状态转换", "status": "passed"},
  {"id": "AC-04", "desc": "实现 maxConcurrent=3 并发控制（activeUploadCount + processQueue）", "status": "passed"},
  {"id": "AC-05", "desc": "实现 removeTask / clearCompleted 队列清理", "status": "passed"},
  {"id": "AC-06", "desc": "实现 loadItems 加载 folders + documents", "status": "passed"},
  {"id": "AC-07", "desc": "实现 deleteDocument / renameDocument / moveDocument", "status": "passed"},
  {"id": "AC-08", "desc": "实现 createFolder / renameFolder / deleteFolder", "status": "passed"},
  {"id": "AC-09", "desc": "实现 breadcrumb 从 folders 和 currentFolderId 计算路径", "status": "passed"},
  {"id": "AC-10", "desc": "并发控制边界：队列空、全部失败、部分成功场景", "status": "passed"}
]}
