{
  "issue_id": "q-26",
  "version": 1,
  "updated_at": "2026-06-06",
  "items": [
    {"id": "AC-01", "desc": "playwright.global-teardown.ts 增加 cleanupDatabase() 调用，测试结束后清理所有业务表", "status": "passed"},
    {"id": "AC-02", "desc": "fixtures/auth.ts 增加 deleteTestUser() 方法，支持按 email 或 id 删除测试用户", "status": "passed"},
    {"id": "AC-03", "desc": "关键 E2E 测试文件增加 test.afterEach 调用 cleanupDatabase()", "status": "passed"},
    {"id": "AC-04", "desc": "运行 pnpm test:e2e，所有 E2E 测试通过", "status": "passed"},
    {"id": "AC-05", "desc": "运行 E2E 测试两次，验证第二次运行时 users 表无上一轮残留数据", "status": "passed"}
  ]
}
